README.md
setup.py
helloword/__init__.py
helloword/say_hello.py
pypi_testah.egg-info/PKG-INFO
pypi_testah.egg-info/SOURCES.txt
pypi_testah.egg-info/dependency_links.txt
pypi_testah.egg-info/top_level.txt